mfdfa1000hz/__init__.py
mfdfa1000hz/mfdfa1000hz.py
mfdfa1000hz-0.1.0.dist-info/METADATA
mfdfa1000hz-0.1.0.dist-info/WHEEL
mfdfa1000hz-0.1.0.dist-info/top_level.txt
mfdfa1000hz-0.1.0.dist-info/RECORD
